Metadata-Version: 1.0
Name: distributionsShiva
Version: 0.1
Summary: Gaussian distributions
Home-page: UNKNOWN
Author: Samarth Srivastava
Author-email: UNKNOWN
License: UNKNOWN
Platform: UNKNOWN
